oai_analysis/__about__.py
oai_analysis/__init__.py
oai_analysis/analysis_object.py
oai_analysis/dask_processing.py
oai_analysis/mesh_processing.py
oai_analysis/registration.py
oai_analysis/utils.py
oai_analysis/segmentation/__init__.py
oai_analysis/segmentation/image_transforms.py
oai_analysis/segmentation/module_parameters.py
oai_analysis/segmentation/networks.py
oai_analysis/segmentation/segmenter.py
oai_analysis/segmentation/utils.py
oai_analysis-2.0.0.dist-info/METADATA
oai_analysis-2.0.0.dist-info/WHEEL
oai_analysis-2.0.0.dist-info/licenses/LICENSE
oai_analysis-2.0.0.dist-info/RECORD
