Metadata-Version: 2.1
Name: oai-analysis
Version: 2.0.0
Summary: Image analysis for the Osteoarthritis Initiative (OAI) knee magnetic resonance image (MRI) dataset.
Project-URL: Documentation, https://github.com/uncbiag/OAI_analysis_2#readme
Project-URL: Issues, https://github.com/uncbiag/OAI_analysis_2/issues
Project-URL: Source, https://github.com/uncbiag/OAI_analysis_2
Author-email: Marc Niethammer <mn@cs.unc.edu>, Hastings Greer <hastings.greer@gmail.com>, Matt McCormick <matt@mmmccormick.com>, Pranjal Sahu <pranjalsahu5@gmail.com>
License-Expression: MIT
License-File: LICENSE
Classifier: Development Status :: 4 - Beta
Classifier: Programming Language :: Python
Classifier: Programming Language :: Python :: 3.8
Classifier: Programming Language :: Python :: 3.9
Classifier: Programming Language :: Python :: 3.10
Classifier: Programming Language :: Python :: 3.11
Classifier: Programming Language :: Python :: Implementation :: CPython
Classifier: Programming Language :: Python :: Implementation :: PyPy
Requires-Python: >=3.8
Requires-Dist: girder-client
Requires-Dist: icon-registration==0.3.4
Requires-Dist: itk==5.3
Requires-Dist: scikit-image
Requires-Dist: torch
Requires-Dist: trimesh
Requires-Dist: vtk
